dvhaedit/__init__.py
dvhaedit/_version.py
dvhaedit/data_table.py
dvhaedit/dialogs.py
dvhaedit/dicom_editor.py
dvhaedit/dynamic_value.py
dvhaedit/main.py
dvhaedit/options.py
dvhaedit/paths.py
dvhaedit/threading.py
dvhaedit/threads.py
dvhaedit/utilities.py
dvhaedit/resources/dynamic_value_help.txt
dvhaedit/resources/icons/dvha-edit.icns
dvhaedit/resources/icons/dvha-edit.ico
dvhaedit/resources/icons/dvha-edit_frame.ico
dvha_edit-0.7.post1.dist-info/LICENSE.txt
dvha_edit-0.7.post1.dist-info/METADATA
dvha_edit-0.7.post1.dist-info/WHEEL
dvha_edit-0.7.post1.dist-info/entry_points.txt
dvha_edit-0.7.post1.dist-info/top_level.txt
dvha_edit-0.7.post1.dist-info/RECORD
