Metadata-Version: 2.1
Name: dvha-edit
Version: 0.7.post1
Summary: Simple DICOM tag editor built with wxPython and pydicom
Home-page: https://github.com/cutright/DVHA-DICOM-Editor
Author: Dan Cutright
Author-email: dan.cutright@gmail.com
Maintainer: Dan Cutright
Maintainer-email: dan.cutright@gmail.com
License: MIT License
Download-URL: https://github.com/cutright/DVHA-DICOM-Editor/archive/master.zip
Keywords: dicom,wxpython,pydicom,pyinstaller
Platform: UNKNOWN
Classifier: License :: OSI Approved :: MIT License
Classifier: Intended Audience :: End Users/Desktop
Classifier: Intended Audience :: Healthcare Industry
Classifier: Intended Audience :: Science/Research
Classifier: Natural Language :: English
Classifier: Development Status :: 4 - Beta
Classifier: Programming Language :: Python
Classifier: Programming Language :: Python :: 3 :: Only
Classifier: Operating System :: OS Independent
Classifier: Topic :: Scientific/Engineering :: Medical Science Apps.
Classifier: Topic :: Scientific/Engineering :: Physics
Requires-Python: >3.5
Requires-Dist: wxPython (<4.1.0,>=4.0.4)
Requires-Dist: pydicom (>=1.4)
Requires-Dist: pypubsub
